{"component":"loteria","level":"error","message":"venderBoletos.loteria.error 99970-ChilkatLog:\r\n  ReceiveToCRLF:\r\n    DllDate: Jan 21 2015\r\n    ChilkatVersion: 9.5.0.47\r\n    UnlockPrefix: SIPECMSocket\r\n    Username: JBG15PP03:usrmtfrads\r\n    Architecture: Little Endian; 64-bit\r\n    Language: .NET 2.0 / x64\r\n    VerboseLogging: 0\r\n    fd: 0xac4\r\n    objectId: 980\r\n    Timeout waiting to read socket or accept connection\r\n    timeoutMs: 20000\r\n    recvUntilMatch: Socket operation timeout.\r\n    Failed.\r\n  --ReceiveToCRLF\r\n--ChilkatLog\r\n","timestamp":"2021-10-12 02:02:40"}
{"component":"loteria","level":"error","message":"autenticarUsuario.error 2627-Violation of PRIMARY KEY constraint 'PK_Registro'. Cannot insert duplicate key in object 'Seguridad.Seg_Registro'. The duplicate key value is (sitiowebprep, 00212612052021151001002126120115, 192.168.1.13).\r\nThe statement has been terminated.,","timestamp":"2021-10-12 06:15:03"}
{"component":"loteria","level":"error","message":"autenticarUsuario.error 2627-Violation of PRIMARY KEY constraint 'PK_Registro'. Cannot insert duplicate key in object 'Seguridad.Seg_Registro'. The duplicate key value is (sitiowebprep, 09308612062021151001093086120115, 192.168.1.13).\r\nThe statement has been terminated.,","timestamp":"2021-10-12 07:15:03"}
{"component":"loteria","data":{"$xml":"\n        <PI_DatosXml>\n        <![CDATA[\n          <mt>\n            <c>\n              <aplicacion>25</aplicacion>\n              <transaccion>8</transaccion>\n              <usuario>0909999906</usuario>\n              <maquina>undefined</maquina>\n              <codError>0</codError>\n              <msgError />\n              <medio>17</medio>\n              <token>59498720092021201045594987204520</token>\n              <operacion>1634751112525</operacion>\n            </c>\n            <i>\n              <MedioId>17</MedioId>\n              <JuegoId>1</JuegoId>\n            </i>\n          </mt>\n          ]]>\n        </PI_DatosXml>\n        "},"errorMessage":"50000-Usuario sin token de sesion valido. 0909999906","level":"error","message":"consultarSorteosDisponibles.loteria.error","timestamp":"2021-10-20 13:31:53"}
{"component":"loteria","data":{"$xml":"\n        <PI_DatosXml>\n        <![CDATA[\n          <mt>\n            <c>\n              <aplicacion>25</aplicacion>\n              <transaccion>8</transaccion>\n              <usuario>0909999906</usuario>\n              <maquina>undefined</maquina>\n              <codError>0</codError>\n              <msgError />\n              <medio>17</medio>\n              <token>23876920122021311059248769205931</token>\n              <operacion>1634766480089</operacion>\n            </c>\n            <i>\n              <MedioId>17</MedioId>\n              <JuegoId>1</JuegoId>\n            </i>\n          </mt>\n          ]]>\n        </PI_DatosXml>\n        "},"errorMessage":"50000-Usuario sin token de sesion valido. 0909999906","level":"error","message":"consultarSorteosDisponibles.loteria.error","timestamp":"2021-10-20 17:48:02"}
{"component":"loteria","level":"error","message":"eliminarReservas.loteria.error 65108-Error procesando reserva: La reserva ingresada no existe, está anulada o vendida.,","timestamp":"2021-10-20 17:57:45"}
{"component":"loteria","level":"error","message":"eliminarReservas.loteria.error 65108-Error procesando reserva: La reserva ingresada no existe, está anulada o vendida.,","timestamp":"2021-10-20 17:57:56"}
{"component":"loteria","data":{"$xml":"\n        <PI_DatosXml>\n        <![CDATA[\n          <mt>\n    <c>\n      <aplicacion>25</aplicacion>\n      <transaccion>9</transaccion>\n      <usuario>0909999906</usuario>\n      <maquina>undefined</maquina>\n      <codError>0</codError>\n      <msgError />\n      <medio>17</medio>\n      <token>5280521012021221015527805211522</token>\n      <operacion>1634797361353</operacion>\n    </c>\n    <i>\n    <MedioId>17</MedioId>\n    <JuegoId>1</JuegoId>\n      <SorteoId>6691</SorteoId>\n      <Combinacion>_____</Combinacion>\n      <Registros>96</Registros>\n      <UsuarioId>0909999906</UsuarioId>\n      <CombFigura></CombFigura>\n      <Sugerir>True</Sugerir>\n    </i>\n  </mt>\t\n          ]]>\n        </PI_DatosXml>\n        "},"errorMessage":"50000-Usuario sin token de sesion valido. 0909999906","level":"error","message":"obtenerCombinacionesDisponibles.loteria.error","timestamp":"2021-10-21 02:22:42"}
{"component":"loteria","level":"error","message":"eliminarReservas.loteria.error 65108-Error procesando reserva: La reserva ingresada no existe, está anulada o vendida.,","timestamp":"2021-10-21 02:23:21"}
{"component":"loteria","level":"error","message":"eliminarReservas.loteria.error 65108-Error procesando reserva: La reserva ingresada no existe, está anulada o vendida.,","timestamp":"2021-10-21 02:37:29"}
{"component":"loteria","level":"error","message":"eliminarReservas.loteria.error 65108-Error procesando reserva: La reserva ingresada no existe, está anulada o vendida.,","timestamp":"2021-10-21 02:37:44"}
{"component":"loteria","data":{"$xml":"\n        <PI_DatosXml>\n        <![CDATA[\n          <mt>\n    <c>\n      <aplicacion>25</aplicacion>\n      <transaccion>9</transaccion>\n      <usuario>0909999906</usuario>\n      <maquina>undefined</maquina>\n      <codError>0</codError>\n      <msgError />\n      <medio>17</medio>\n      <token>90365121022021001011903651211100</token>\n      <operacion>1634799636751</operacion>\n    </c>\n    <i>\n    <MedioId>17</MedioId>\n    <JuegoId>2</JuegoId>\n      <SorteoId>2606</SorteoId>\n      <Combinacion>______</Combinacion>\n      <Registros>96</Registros>\n      <UsuarioId>0909999906</UsuarioId>\n      <CombFigura></CombFigura>\n      <Sugerir>True</Sugerir>\n    </i>\n  </mt>\t\n          ]]>\n        </PI_DatosXml>\n        "},"errorMessage":"99970-ChilkatLog:\r\n  ReceiveToCRLF:\r\n    DllDate: Jan 21 2015\r\n    ChilkatVersion: 9.5.0.47\r\n    UnlockPrefix: SIPECMSocket\r\n    Username: JBG21WS13:usrmtframe\r\n    Architecture: Little Endian; 64-bit\r\n    Language: .NET 2.0 / x64\r\n    VerboseLogging: 0\r\n    fd: 0x9dc\r\n    objectId: 267199\r\n    Timeout waiting to read socket or accept connection\r\n    timeoutMs: 20000\r\n    recvUntilMatch: Socket operation timeout.\r\n    Failed.\r\n  --ReceiveToCRLF\r\n--ChilkatLog\r\n","level":"error","message":"obtenerCombinacionesDisponibles.loteria.error","timestamp":"2021-10-21 03:00:57"}
